Metadata-Version: 2.1
Name: easy-alpaca
Version: 0.2
Summary: A library for the Alpaca Trading and Data API
Home-page: https://github.com/ltanedo/easy-alpaca.git
Download-URL: https://github.com/ltanedo/easy-alpaca/archive/refs/tags/v_02.tar.gz
Author: lloydtan
Author-email: lloydtan@buffalo.edu
License: MIT
Keywords: python,algo,trading,alpaca,brokerage,stocks,stock
Platform: UNKNOWN
Classifier: Development Status :: 3 - Alpha
Classifier: Intended Audience :: Developers
Classifier: Topic :: Software Development :: Build Tools
Classifier: License :: OSI Approved :: MIT License
Classifier: Programming Language :: Python :: 3
Classifier: Programming Language :: Python :: 3.4
Classifier: Programming Language :: Python :: 3.5
Classifier: Programming Language :: Python :: 3.6
Classifier: Programming Language :: Python :: 3.8
